sorted_chain/__init__.py
sorted_chain/_version.py
sorted_chain/sorted_chain.py
sorted_chain/version.py
sorted_chain/test/__init__.py
sorted_chain/test/test_sorted_chain.py
sorted_chain/test/test_with_doctest.py
sorted_chain-0.0.2.dist-info/METADATA
sorted_chain-0.0.2.dist-info/WHEEL
sorted_chain-0.0.2.dist-info/licenses/LICENSE
sorted_chain-0.0.2.dist-info/RECORD
