Metadata-Version: 2.3
Name: sorted_chain
Version: 0.0.2
Summary: itertools.chain for sorted and endless iterators
Project-URL: Homepage, https://github.com/niccokunzmann/sorted_chain/
Project-URL: Repository, https://github.com/niccokunzmann/sorted_chain/
Project-URL: source_archive, https://github.com/niccokunzmann/sorted_chain/archive/51423d554fa96babdcada253e908b4e9da5794fd.zip
Project-URL: Issues, https://github.com/niccokunzmann/sorted_chain/issues
Project-URL: Documentation, https://github.com/niccokunzmann/sorted_chain/
Project-URL: Changelog, https://github.com/niccokunzmann/sorted_chain/#changelog
Author-email: Nicco Kunzmann <niccokunzmann@rambler.ru>
Maintainer-email: Nicco Kunzmann <niccokunzmann@rambler.ru>
License:                     GNU GENERAL PUBLIC LICENSE
License-File: LICENSE
Keywords: chain,itertools,sort,sorting
Classifier: Development Status :: 5 - Production/Stable
Classifier: Intended Audience :: Developers
Classifier: License :: OSI Approved :: GNU General Public License v3 (GPLv3)
Classifier: Operating System :: OS Independent
Classifier: Programming Language :: Python :: 3.9
Classifier: Programming Language :: Python :: 3.10
Classifier: Programming Language :: Python :: 3.11
Classifier: Programming Language :: Python :: 3.12
Requires-Python: >=3.9
Provides-Extra: test
Requires-Dist: pytest; extra == 'test'
